preset_cli/__init__.py
preset_cli/exceptions.py
preset_cli/lib.py
preset_cli/typing.py
preset_cli/api/__init__.py
preset_cli/api/operators.py
preset_cli/api/clients/__init__.py
preset_cli/api/clients/dbt.py
preset_cli/api/clients/preset.py
preset_cli/api/clients/superset.py
preset_cli/auth/__init__.py
preset_cli/auth/jwt.py
preset_cli/auth/lib.py
preset_cli/auth/main.py
preset_cli/auth/preset.py
preset_cli/auth/superset.py
preset_cli/auth/token.py
preset_cli/cli/__init__.py
preset_cli/cli/export_users.py
preset_cli/cli/main.py
preset_cli/cli/superset/__init__.py
preset_cli/cli/superset/export.py
preset_cli/cli/superset/import_.py
preset_cli/cli/superset/lib.py
preset_cli/cli/superset/main.py
preset_cli/cli/superset/sql.py
preset_cli/cli/superset/sync/__init__.py
preset_cli/cli/superset/sync/main.py
preset_cli/cli/superset/sync/dbt/__init__.py
preset_cli/cli/superset/sync/dbt/command.py
preset_cli/cli/superset/sync/dbt/databases.py
preset_cli/cli/superset/sync/dbt/datasets.py
preset_cli/cli/superset/sync/dbt/exposures.py
preset_cli/cli/superset/sync/dbt/lib.py
preset_cli/cli/superset/sync/dbt/metrics.py
preset_cli/cli/superset/sync/dbt/schemas.py
preset_cli/cli/superset/sync/dj/__init__.py
preset_cli/cli/superset/sync/dj/command.py
preset_cli/cli/superset/sync/dj/lib.py
preset_cli/cli/superset/sync/native/__init__.py
preset_cli/cli/superset/sync/native/command.py
preset_cli-0.3.10.dist-info/licenses/LICENSE.txt
preset_cli-0.3.10.dist-info/METADATA
preset_cli-0.3.10.dist-info/WHEEL
preset_cli-0.3.10.dist-info/entry_points.txt
preset_cli-0.3.10.dist-info/top_level.txt
preset_cli-0.3.10.dist-info/RECORD
