Metadata-Version: 2.4
Name: preset-cli
Version: 0.3.10
Summary: A CLI to interact with Preset (https://preset.io/) workspaces.
Home-page: https://github.com/preset-io/backend-sdk
Author: Beto Dealmeida
Author-email: beto@preset.io
License: Other/Proprietary License
Project-URL: Documentation, https://github.com/preset-io/backend-sdk/blob/master/README.rst
Platform: any
Classifier: Development Status :: 4 - Beta
Classifier: Programming Language :: Python
Classifier: Programming Language :: Python :: 3.10
Classifier: Programming Language :: Python :: 3.11
Classifier: Programming Language :: Python :: 3.12
Classifier: License :: Other/Proprietary License
License-File: LICENSE.txt
Requires-Dist: importlib-metadata; python_version < "3.8"
Requires-Dist: Cython>=0.29.26
Requires-Dist: PyYAML>=6.0
Requires-Dist: appdirs>=1.4.4
Requires-Dist: backoff>=1.10.0
Requires-Dist: beautifulsoup4>=4.10.0
Requires-Dist: click<8.2,>=8.0.3
Requires-Dist: jinja2>=3.0.3
Requires-Dist: marshmallow>=3.17.0
Requires-Dist: numpy>=1.26.0
Requires-Dist: pandas>=2.0.0
Requires-Dist: prison>=0.2.1
Requires-Dist: prompt-toolkit>=3.0.24
Requires-Dist: pygments>=2.11.2
Requires-Dist: python-graphql-client>=0.4.3
Requires-Dist: requests>=2.26.0
Requires-Dist: rich>=12.3.0
Requires-Dist: sqlalchemy<2,>=1.4
Requires-Dist: sqlglot>=26
Requires-Dist: tabulate>=0.8.9
Requires-Dist: typing-extensions>=4.0.1
Requires-Dist: yarl>=1.7.2
Requires-Dist: greenlet>=3.0.0
Requires-Dist: aiohttp>=3.9.0
Provides-Extra: snowflake
Requires-Dist: snowflake-sqlalchemy==1.4.4; extra == "snowflake"
Provides-Extra: testing
Requires-Dist: setuptools; extra == "testing"
Requires-Dist: freezegun; extra == "testing"
Requires-Dist: pytest; extra == "testing"
Requires-Dist: pytest-cov; extra == "testing"
Requires-Dist: pytest-mock; extra == "testing"
Requires-Dist: pyfakefs; extra == "testing"
Requires-Dist: requests-mock; extra == "testing"
Requires-Dist: codespell; extra == "testing"
Requires-Dist: pre-commit; extra == "testing"
Requires-Dist: pip-tools>=6.6.0; extra == "testing"
Requires-Dist: pylint>=3.0; extra == "testing"
Requires-Dist: datajunction; extra == "testing"
Dynamic: license-file
